[
  {
    "forceZup": false,

    "mass": 6000,
    "tensorFactor": 0.2,
    "dragFactor": 0.6,
    "com": [0, 0, 0],

    "zeroThrustAltitude": 120000,
    "minRPM": 1000,
    "maxRPM": 10000,
    "driveRatio": 0.25,
    "engineInertia": 2,
    "startupTime": 3,

    "startAltitude": 2,
    "startTilt": 0,
    "minimumSpeed": 0,

    "parts": [
      {
        "name": "root",
        "type": "root",
        "position": [0, 0, 0],
        "rotation": [0, 0, -90],
        "model": "model.glb",
        "gltf2model": { "url": "model.glb" }
      },

      {
        "name": "frame",
        "type": "frame",
        "collisionPoints": [
          [ 0.0,  1.5, -0.25],
          [ 0.0, -1.5, -0.25],
          [ 1.2,  0.0, -0.25],
          [-1.2,  0.0, -0.25]
        ]
      },

      {
        "name": "body",
        "type": "airfoil",
        "position": [0, 0, 0],
        "liftFactor": 18,
        "dragFactor": 0.2,
        "forceDirection": "X",
        "points": { "forceSourcePoint": [0, 1.2, 0] }
      },

      {
        "name": "leftWing",
        "type": "airfoil",
        "area": 10,
        "forceDirection": "Z",
        "points": { "forceSourcePoint": [-2.5, 0.3, 0] },
        "rotation": [-1, 0, 0],
        "stallIncidence": 15,
        "zeroLiftIncidence": 20,
        "stalls": true
      },

      {
        "name": "rightWing",
        "type": "airfoil",
        "area": 10,
        "forceDirection": "Z",
        "points": { "forceSourcePoint": [2.5, 0.3, 0] },
        "rotation": [-1, 0, 0],
        "stallIncidence": 15,
        "zeroLiftIncidence": 20,
        "stalls": true
      },

      {
        "name": "engine",
        "type": "engine",
        "thrust": 90000,
        "afterBurnerThrust": 180000,
        "forceDirection": "Y",
        "contrail": true,
        "points": {
          "forceSourcePoint": [0, -2.5, 0.0],
          "contrailAnchor": [0, -20, 0.0]
        }
      }
    ],

    "contactProperties": {
      "wheel": { "frictionCoef": 2, "dynamicFriction": 0.01, "rollingFriction": 0.00001, "damping": 1 },
      "frame": { "frictionCoef": 2, "dynamicFriction": 0.01, "damping": 1 },
      "airfoil": { "frictionCoef": 2, "dynamicFriction": 0.01, "damping": 1 }
    },

    "cameras": {
      "follow": { "distance": 25 }
    }
  }
]
